dyntool/__init__.py
dyntool/__main__.py
dyntool/server.py
dyntool-0.1.3.dist-info/METADATA
dyntool-0.1.3.dist-info/WHEEL
dyntool-0.1.3.dist-info/entry_points.txt
dyntool-0.1.3.dist-info/RECORD
